cli/__init__.py
cli/config.py
cli/main.py
cli/oorb_qa_system.py
cli/tool_display.py
cli/tools.py
oorb_cli-1.0.11.dist-info/METADATA
oorb_cli-1.0.11.dist-info/WHEEL
oorb_cli-1.0.11.dist-info/entry_points.txt
oorb_cli-1.0.11.dist-info/top_level.txt
oorb_cli-1.0.11.dist-info/RECORD
