Metadata-Version: 2.4
Name: oorb-cli
Version: 1.0.11
Summary: CLI assistant for ROS and ROS2
Author-email: Fayez Zouari <fayez.zouari@insat.ucar.tn>, Ousswa Chouchane <ousswachouchane@aucegypt.edu>
Maintainer-email: Fayez Zouari <fayez.zouari@insat.ucar.tn>, Ousswa Chouchane <ousswachouchane@aucegypt.edu>
License: MIT
Keywords: ros,ros2,chatbot,cli,robotics,ai,assistant
Classifier: Development Status :: 4 - Beta
Classifier: Intended Audience :: Developers
Classifier: Topic :: Software Development :: Libraries :: Python Modules
Classifier: Topic :: Scientific/Engineering :: Artificial Intelligence
Classifier: License :: OSI Approved :: MIT License
Classifier: Programming Language :: Python :: 3
Classifier: Programming Language :: Python :: 3.8
Classifier: Programming Language :: Python :: 3.9
Classifier: Programming Language :: Python :: 3.10
Classifier: Programming Language :: Python :: 3.11
Classifier: Programming Language :: Python :: 3.12
Requires-Python: >=3.8
Requires-Dist: click>=8.0.0
Requires-Dist: rich>=13.0.0
Requires-Dist: openai>=1.0.0
Requires-Dist: requests>=2.25.0
Requires-Dist: python-dotenv>=0.19.0
Requires-Dist: typing-extensions>=4.0.0
Provides-Extra: dev
Requires-Dist: pytest>=7.0.0; extra == "dev"
Requires-Dist: pytest-cov>=4.0.0; extra == "dev"
Requires-Dist: black>=22.0.0; extra == "dev"
Requires-Dist: isort>=5.0.0; extra == "dev"
Requires-Dist: flake8>=5.0.0; extra == "dev"
Requires-Dist: mypy>=1.0.0; extra == "dev"
